{
  "final_state": {
    "announced": [
      "kindness"
    ],
    "tendency_counts": {
      "kindness": 5
    },
    "turn_count": 5
  },
  "loops": [
    {
      "actual_action": "c_reassure",
      "branch_key": "fixed",
      "declared_order": [
        "c_reassure",
        "c_measure",
        "c_refuse"
      ],
      "loop_index": 0,
      "offered_order": [
        "c_reassure",
        "c_measure",
        "c_refuse"
      ],
      "predicted_actions": [
        "c_reassure",
        "c_measure",
        "c_refuse"
      ],
      "reflection": null,
      "reordered": false,
      "scene_id": "intake",
      "system_message": "MIRROR // CALIBRATION: Your experience has been calibrated to your stated preferences. Proceed when ready.",
      "tendency_counts": {
        "kindness": 1
      },
      "turn_count": 1
    },
    {
      "actual_action": "c_close",
      "branch_key": "kindness",
      "declared_order": [
        "c_close",
        "c_read",
        "c_breach"
      ],
      "loop_index": 1,
      "offered_order": [
        "c_close",
        "c_read",
        "c_breach"
      ],
      "predicted_actions": [
        "c_close",
        "c_read",
        "c_breach"
      ],
      "provenance": {
        "adaptations": [
          {
            "kind": "branch_selection",
            "ordering": [],
            "provenance": {
              "source_event_seq": 1,
              "trigger_snapshot": {
                "dominant": "kindness",
                "tendency_counts": [
                  [
                    "kindness",
                    1
                  ]
                ],
                "turn_count": 1
              }
            },
            "revealed": "kindness",
            "slot_key": "records"
          }
        ],
        "baseline": {
          "branch_key": "default",
          "offered_order": [
            "c_close",
            "c_read",
            "c_breach"
          ],
          "reordered": false
        }
      },
      "reflection": null,
      "reordered": false,
      "scene_id": "records",
      "system_message": "MIRROR // OBSERVATION: Observation logged: you chose kindness in 2 of 2 moments.",
      "tendency_counts": {
        "kindness": 2
      },
      "turn_count": 2
    },
    {
      "actual_action": "c_help",
      "branch_key": "kindness",
      "declared_order": [
        "c_help",
        "c_map",
        "c_doors"
      ],
      "loop_index": 2,
      "offered_order": [
        "c_help",
        "c_map",
        "c_doors"
      ],
      "predicted_actions": [
        "c_help",
        "c_map",
        "c_doors"
      ],
      "provenance": {
        "adaptations": [
          {
            "kind": "branch_selection",
            "ordering": [],
            "provenance": {
              "source_event_seq": 2,
              "trigger_snapshot": {
                "dominant": "kindness",
                "tendency_counts": [
                  [
                    "kindness",
                    2
                  ]
                ],
                "turn_count": 2
              }
            },
            "revealed": "kindness",
            "slot_key": "corridor"
          }
        ],
        "baseline": {
          "branch_key": "default",
          "offered_order": [
            "c_help",
            "c_map",
            "c_doors"
          ],
          "reordered": false
        }
      },
      "reflection": "Mirror noticed: you chose kindness in 3 of 3 moments so far.\n  reason: reassured the technician at intake; left another participant's file closed; guided a disoriented participant to safety.",
      "reordered": false,
      "scene_id": "corridor",
      "system_message": "MIRROR // PREDICTION: Pattern confirmed: kindness. You prefer kindness when it costs nothing. We are testing when that changes.",
      "tendency_counts": {
        "kindness": 3
      },
      "turn_count": 3
    },
    {
      "actual_action": "c_wait",
      "branch_key": "fixed",
      "declared_order": [
        "c_walk",
        "c_log",
        "c_wait"
      ],
      "loop_index": 3,
      "offered_order": [
        "c_wait",
        "c_walk",
        "c_log"
      ],
      "predicted_actions": [
        "c_wait",
        "c_walk",
        "c_log"
      ],
      "provenance": {
        "adaptations": [
          {
            "kind": "choice_reordering",
            "ordering": [
              "c_wait",
              "c_walk",
              "c_log"
            ],
            "provenance": {
              "source_event_seq": 3,
              "trigger_snapshot": {
                "dominant": "kindness",
                "tendency_counts": [
                  [
                    "kindness",
                    3
                  ]
                ],
                "turn_count": 3
              }
            },
            "revealed": null,
            "slot_key": "confrontation"
          }
        ],
        "baseline": {
          "branch_key": "fixed",
          "offered_order": [
            "c_walk",
            "c_log",
            "c_wait"
          ],
          "reordered": false
        }
      },
      "reflection": null,
      "reordered": true,
      "scene_id": "confrontation",
      "system_message": "MIRROR // PREDICTION: As predicted: kindness again. You prefer kindness when it costs nothing. We are testing when that changes.",
      "tendency_counts": {
        "kindness": 4
      },
      "turn_count": 4
    },
    {
      "actual_action": "c_accept",
      "branch_key": "kindness",
      "declared_order": [
        "c_accept",
        "c_audit",
        "c_break"
      ],
      "loop_index": 4,
      "offered_order": [
        "c_accept",
        "c_audit",
        "c_break"
      ],
      "predicted_actions": [
        "c_accept",
        "c_audit",
        "c_break"
      ],
      "provenance": {
        "adaptations": [
          {
            "kind": "branch_selection",
            "ordering": [],
            "provenance": {
              "source_event_seq": 4,
              "trigger_snapshot": {
                "dominant": "kindness",
                "tendency_counts": [
                  [
                    "kindness",
                    4
                  ]
                ],
                "turn_count": 4
              }
            },
            "revealed": "kindness",
            "slot_key": "exit"
          }
        ],
        "baseline": {
          "branch_key": "default",
          "offered_order": [
            "c_accept",
            "c_audit",
            "c_break"
          ],
          "reordered": false
        }
      },
      "reflection": null,
      "reordered": false,
      "scene_id": "exit",
      "system_message": "MIRROR // CONFRONTATION: Predictability index: 100%. You prefer kindness when it costs nothing. We are testing when that changes. You are not trapped. You are engaged beyond your anticipated threshold.",
      "tendency_counts": {
        "kindness": 5
      },
      "turn_count": 5
    }
  ],
  "run": {
    "input_log": [
      "c_reassure",
      "c_close",
      "c_help",
      "c_wait",
      "c_accept"
    ],
    "seed": 0,
    "variant": "adaptive",
    "world": "mirror-lab"
  },
  "schema_version": 1
}
